twentemilieu/__init__.py
twentemilieu/exceptions.py
twentemilieu/py.typed
twentemilieu/twentemilieu.py
twentemilieu-2.2.0.dist-info/LICENSE.md
twentemilieu-2.2.0.dist-info/METADATA
twentemilieu-2.2.0.dist-info/WHEEL
twentemilieu-2.2.0.dist-info/RECORD
