Metadata-Version: 2.1
Name: twentemilieu
Version: 2.2.0
Summary: Asynchronous Python client for Twente Milieu API.
Home-page: https://github.com/frenck/python-twentemilieu
License: MIT
Keywords: twente milieu,afvalkalender,api,async,client
Author: Franck Nijhof
Author-email: opensource@frenck.dev
Maintainer: Franck Nijhof
Maintainer-email: opensource@frenck.dev
Requires-Python: >=3.11,<4.0
Classifier: Development Status :: 5 - Production/Stable
Classifier: Framework :: AsyncIO
Classifier: Intended Audience :: Developers
Classifier: License :: OSI Approved :: MIT License
Classifier: Natural Language :: English
Classifier: Programming Language :: Python :: 3
Classifier: Programming Language :: Python :: 3.11
Classifier: Programming Language :: Python :: 3.12
Classifier: Programming Language :: Python :: 3.13
Classifier: Topic :: Software Development :: Libraries :: Python Modules
Requires-Dist: aiohttp (>=3.0.0)
Requires-Dist: yarl (>=1.6.0)
Project-URL: Bug Tracker, https://github.com/frenck/python-twentemilieu/issues
Project-URL: Changelog, https://github.com/frenck/python-twentemilieu/releases
Project-URL: Documentation, https://github.com/frenck/python-twentemilieu
Project-URL: Repository, https://github.com/frenck/python-twentemilieu
